{
  "openapi": "3.0.0",
  "info": {
    "title": "PrometheOS API",
    "description": "API for AI agent interaction with the PrometheOS",
    "version": "1.0.0"
  },
  "paths": {
    "/api/services/open": {
      "post": {
        "summary": "Open App",
        "description": "Launch an app by its ID",
        "operationId": "services_open",
        "requestBody": {
          "required": true,
          "content": {
            "application/json": {
              "schema": {
                "type": "object",
                "properties": {
                  "appId": {
                    "type": "string",
                    "description": "The ID of the app to launch"
                  }
                },
                "required": [
                  "appId"
                ]
              }
            }
          }
        },
        "responses": {
          "200": {
            "description": "Successful operation",
            "content": {
              "application/json": {
                "schema": {
                  "type": "object",
                  "properties": {
                    "success": {
                      "type": "boolean",
                      "description": "Whether the operation was successful"
                    },
                    "data": {
                      "type": "object",
                      "description": "Result data from the operation"
                    }
                  }
                }
              }
            }
          },
          "400": {
            "description": "Error response",
            "content": {
              "application/json": {
                "schema": {
                  "type": "object",
                  "properties": {
                    "success": {
                      "type": "boolean",
                      "example": false,
                      "description": "Operation failed"
                    },
                    "error": {
                      "type": "string",
                      "description": "Error message"
                    }
                  }
                }
              }
            }
          }
        },
        "tags": [
          "System"
        ]
      }
    },
    "/api/services/kill": {
      "post": {
        "summary": "Kill App",
        "description": "Closes an app by its ID",
        "operationId": "services_kill",
        "requestBody": {
          "required": true,
          "content": {
            "application/json": {
              "schema": {
                "type": "object",
                "properties": {
                  "appId": {
                    "type": "string",
                    "description": "The ID of the app to close"
                  }
                },
                "required": [
                  "appId"
                ]
              }
            }
          }
        },
        "responses": {
          "200": {
            "description": "Successful operation",
            "content": {
              "application/json": {
                "schema": {
                  "type": "object",
                  "properties": {
                    "success": {
                      "type": "boolean",
                      "description": "Whether the operation was successful"
                    },
                    "data": {
                      "type": "object",
                      "description": "Result data from the operation"
                    }
                  }
                }
              }
            }
          },
          "400": {
            "description": "Error response",
            "content": {
              "application/json": {
                "schema": {
                  "type": "object",
                  "properties": {
                    "success": {
                      "type": "boolean",
                      "example": false,
                      "description": "Operation failed"
                    },
                    "error": {
                      "type": "string",
                      "description": "Error message"
                    }
                  }
                }
              }
            }
          }
        },
        "tags": [
          "System"
        ]
      }
    },
    "/api/services/restart": {
      "post": {
        "summary": "Restart App",
        "description": "Restarts an app by closing and reopening it",
        "operationId": "services_restart",
        "requestBody": {
          "required": true,
          "content": {
            "application/json": {
              "schema": {
                "type": "object",
                "properties": {
                  "appId": {
                    "type": "string",
                    "description": "The ID of the app to restart"
                  }
                },
                "required": [
                  "appId"
                ]
              }
            }
          }
        },
        "responses": {
          "200": {
            "description": "Successful operation",
            "content": {
              "application/json": {
                "schema": {
                  "type": "object",
                  "properties": {
                    "success": {
                      "type": "boolean",
                      "description": "Whether the operation was successful"
                    },
                    "data": {
                      "type": "object",
                      "description": "Result data from the operation"
                    }
                  }
                }
              }
            }
          },
          "400": {
            "description": "Error response",
            "content": {
              "application/json": {
                "schema": {
                  "type": "object",
                  "properties": {
                    "success": {
                      "type": "boolean",
                      "example": false,
                      "description": "Operation failed"
                    },
                    "error": {
                      "type": "string",
                      "description": "Error message"
                    }
                  }
                }
              }
            }
          }
        },
        "tags": [
          "System"
        ]
      }
    },
    "/api/services/notify": {
      "post": {
        "summary": "Notify",
        "description": "Show a notification on screen",
        "operationId": "services_notify",
        "requestBody": {
          "required": true,
          "content": {
            "application/json": {
              "schema": {
                "type": "object",
                "properties": {
                  "message": {
                    "type": "string",
                    "description": "The notification message to display"
                  },
                  "type": {
                    "type": "string",
                    "description": "Notification engine to use",
                    "enum": [
                      "radix",
                      "sonner"
                    ]
                  }
                },
                "required": [
                  "message"
                ]
              }
            }
          }
        },
        "responses": {
          "200": {
            "description": "Successful operation",
            "content": {
              "application/json": {
                "schema": {
                  "type": "object",
                  "properties": {
                    "success": {
                      "type": "boolean",
                      "description": "Whether the operation was successful"
                    },
                    "data": {
                      "type": "object",
                      "description": "Result data from the operation"
                    }
                  }
                }
              }
            }
          },
          "400": {
            "description": "Error response",
            "content": {
              "application/json": {
                "schema": {
                  "type": "object",
                  "properties": {
                    "success": {
                      "type": "boolean",
                      "example": false,
                      "description": "Operation failed"
                    },
                    "error": {
                      "type": "string",
                      "description": "Error message"
                    }
                  }
                }
              }
            }
          }
        },
        "tags": [
          "System"
        ]
      }
    },
    "/api/services/openDialog": {
      "post": {
        "summary": "Open Dialog",
        "description": "Opens a confirmation dialog and returns whether the user confirmed",
        "operationId": "services_openDialog",
        "requestBody": {
          "required": true,
          "content": {
            "application/json": {
              "schema": {
                "type": "object",
                "properties": {
                  "title": {
                    "type": "string",
                    "description": "Dialog title"
                  },
                  "description": {
                    "type": "string",
                    "description": "Dialog description"
                  },
                  "confirmLabel": {
                    "type": "string",
                    "description": "Confirm button label"
                  },
                  "cancelLabel": {
                    "type": "string",
                    "description": "Cancel button label"
                  }
                },
                "required": [
                  "title"
                ]
              }
            }
          }
        },
        "responses": {
          "200": {
            "description": "Successful operation",
            "content": {
              "application/json": {
                "schema": {
                  "type": "object",
                  "properties": {
                    "success": {
                      "type": "boolean",
                      "description": "Whether the operation was successful"
                    },
                    "data": {
                      "type": "object",
                      "description": "Result data from the operation"
                    }
                  }
                }
              }
            }
          },
          "400": {
            "description": "Error response",
            "content": {
              "application/json": {
                "schema": {
                  "type": "object",
                  "properties": {
                    "success": {
                      "type": "boolean",
                      "example": false,
                      "description": "Operation failed"
                    },
                    "error": {
                      "type": "string",
                      "description": "Error message"
                    }
                  }
                }
              }
            }
          }
        },
        "tags": [
          "System"
        ]
      }
    },
    "/api/services/waitForEvent": {
      "post": {
        "summary": "Wait For Event",
        "description": "Waits for the specified event to be emitted or until the timeout is reached",
        "operationId": "services_waitForEvent",
        "requestBody": {
          "required": true,
          "content": {
            "application/json": {
              "schema": {
                "type": "object",
                "properties": {
                  "eventId": {
                    "type": "string",
                    "description": "The name of the event to wait for"
                  },
                  "timeout": {
                    "type": "number",
                    "description": "Timeout in milliseconds (optional, default is infinite)"
                  }
                },
                "required": [
                  "eventId"
                ]
              }
            }
          }
        },
        "responses": {
          "200": {
            "description": "Successful operation",
            "content": {
              "application/json": {
                "schema": {
                  "type": "object",
                  "properties": {
                    "success": {
                      "type": "boolean",
                      "description": "Whether the operation was successful"
                    },
                    "data": {
                      "type": "object",
                      "description": "Result data from the operation"
                    }
                  }
                }
              }
            }
          },
          "400": {
            "description": "Error response",
            "content": {
              "application/json": {
                "schema": {
                  "type": "object",
                  "properties": {
                    "success": {
                      "type": "boolean",
                      "example": false,
                      "description": "Operation failed"
                    },
                    "error": {
                      "type": "string",
                      "description": "Error message"
                    }
                  }
                }
              }
            }
          }
        },
        "tags": [
          "System"
        ]
      }
    },
    "/api/services/listEvents": {
      "post": {
        "summary": "List Events",
        "description": "Returns all known event names",
        "operationId": "services_listEvents",
        "responses": {
          "200": {
            "description": "Successful operation",
            "content": {
              "application/json": {
                "schema": {
                  "type": "object",
                  "properties": {
                    "success": {
                      "type": "boolean",
                      "description": "Whether the operation was successful"
                    },
                    "data": {
                      "type": "object",
                      "description": "Result data from the operation"
                    }
                  }
                }
              }
            }
          },
          "400": {
            "description": "Error response",
            "content": {
              "application/json": {
                "schema": {
                  "type": "object",
                  "properties": {
                    "success": {
                      "type": "boolean",
                      "example": false,
                      "description": "Operation failed"
                    },
                    "error": {
                      "type": "string",
                      "description": "Error message"
                    }
                  }
                }
              }
            }
          }
        },
        "tags": [
          "System"
        ]
      }
    }
  },
  "components": {
    "schemas": {}
  }
}